nvidia_rag/__init__.py
nvidia_rag/ingestor_server/__init__.py
nvidia_rag/ingestor_server/health.py
nvidia_rag/ingestor_server/main.py
nvidia_rag/ingestor_server/nvingest.py
nvidia_rag/ingestor_server/server.py
nvidia_rag/ingestor_server/task_handler.py
nvidia_rag/rag_server/__init__.py
nvidia_rag/rag_server/health.py
nvidia_rag/rag_server/main.py
nvidia_rag/rag_server/prompt.yaml
nvidia_rag/rag_server/query_decomposition.py
nvidia_rag/rag_server/reflection.py
nvidia_rag/rag_server/response_generator.py
nvidia_rag/rag_server/server.py
nvidia_rag/rag_server/tracing.py
nvidia_rag/rag_server/validation.py
nvidia_rag/rag_server/vlm.py
nvidia_rag/utils/__init__.py
nvidia_rag/utils/common.py
nvidia_rag/utils/configuration.py
nvidia_rag/utils/configuration_wizard.py
nvidia_rag/utils/embedding.py
nvidia_rag/utils/filter_expression_generator.py
nvidia_rag/utils/filter_grammar.lark
nvidia_rag/utils/llm.py
nvidia_rag/utils/metadata_validation.py
nvidia_rag/utils/minio_operator.py
nvidia_rag/utils/reranker.py
nvidia_rag/utils/vdb/__init__.py
nvidia_rag/utils/vdb/vdb_base.py
nvidia_rag/utils/vdb/elasticsearch/__init__.py
nvidia_rag/utils/vdb/elasticsearch/elastic_vdb.py
nvidia_rag/utils/vdb/elasticsearch/es_queries.py
nvidia_rag/utils/vdb/milvus/__init__.py
nvidia_rag/utils/vdb/milvus/milvus_vdb.py
nvidia_rag-2.3.0.dist-info/licenses/LICENSE
observability/langchain_callback_handler.py
observability/langchain_instrumentor.py
observability/otel_metrics.py
nvidia_rag-2.3.0.dist-info/METADATA
nvidia_rag-2.3.0.dist-info/WHEEL
nvidia_rag-2.3.0.dist-info/top_level.txt
nvidia_rag-2.3.0.dist-info/RECORD
