Metadata-Version: 2.4
Name: nvidia_rag
Version: 2.3.0
Summary: This blueprint serves as a reference solution for a foundational Retrieval Augmented Generation (RAG) pipeline.
Author-email: NVIDIA RAG <foundational-rag-dev@exchange.nvidia.com>
License-Expression: Apache-2.0
Project-URL: Homepage, https://github.com/NVIDIA-AI-Blueprints/rag
Project-URL: Documentation, https://github.com/NVIDIA-AI-Blueprints/rag/blob/main/README.md
Requires-Python: >=3.12
License-File: LICENSE
Requires-Dist: bleach==6.2.0
Requires-Dist: dataclass-wizard==0.27.0
Requires-Dist: fastapi==0.115.5
Requires-Dist: langchain>=0.3.27
Requires-Dist: langchain-community>=0.3.27
Requires-Dist: langchain-milvus>=0.2.1
Requires-Dist: langchain-nvidia-ai-endpoints>=0.3.17
Requires-Dist: minio==7.2.15
Requires-Dist: pdfplumber>=0.6
Requires-Dist: pydantic>=2.11.7
Requires-Dist: pymilvus==2.5.8
Requires-Dist: pymilvus-model==0.3.2
Requires-Dist: python-multipart==0.0.18
Requires-Dist: pyyaml==6.0.2
Requires-Dist: uvicorn[standard]==0.32.0
Requires-Dist: langchain-core>=0.3.72
Requires-Dist: redis==5.2.1
Requires-Dist: protobuf>=5.29.5
Requires-Dist: langchain-elasticsearch==0.3.2
Requires-Dist: lark>=1.2.2
Requires-Dist: python-dateutil>=2.9.0.post0
Requires-Dist: nv-ingest-api==25.9.0
Requires-Dist: nv-ingest-client==25.9.0
Requires-Dist: tritonclient==2.57.0
Provides-Extra: rag
Requires-Dist: langchain-openai==0.2.8; extra == "rag"
Requires-Dist: opentelemetry-api==1.29.0; extra == "rag"
Requires-Dist: opentelemetry-exporter-otlp==1.29.0; extra == "rag"
Requires-Dist: opentelemetry-exporter-prometheus==0.50b0; extra == "rag"
Requires-Dist: opentelemetry-instrumentation==0.50b0; extra == "rag"
Requires-Dist: opentelemetry-instrumentation-fastapi==0.50b0; extra == "rag"
Requires-Dist: opentelemetry-instrumentation-milvus==0.36.0; extra == "rag"
Requires-Dist: opentelemetry-processor-baggage==0.50b0; extra == "rag"
Requires-Dist: opentelemetry-sdk==1.29.0; extra == "rag"
Requires-Dist: opentelemetry-sdk-extension-prometheus-multiprocess==1.0.0; extra == "rag"
Requires-Dist: prometheus-client==0.20.0; extra == "rag"
Requires-Dist: azure-core>=1.35.0; extra == "rag"
Requires-Dist: azure-storage-blob>=12.26.0; extra == "rag"
Requires-Dist: pyarrow>=21.0.0; extra == "rag"
Provides-Extra: ingest
Requires-Dist: overrides==7.7.0; extra == "ingest"
Requires-Dist: tqdm==4.67.1; extra == "ingest"
Requires-Dist: opentelemetry-api==1.29.0; extra == "ingest"
Requires-Dist: opentelemetry-exporter-otlp==1.29.0; extra == "ingest"
Requires-Dist: opentelemetry-exporter-prometheus==0.50b0; extra == "ingest"
Requires-Dist: opentelemetry-instrumentation==0.50b0; extra == "ingest"
Requires-Dist: opentelemetry-instrumentation-fastapi==0.50b0; extra == "ingest"
Requires-Dist: opentelemetry-instrumentation-milvus==0.36.0; extra == "ingest"
Requires-Dist: opentelemetry-processor-baggage==0.50b0; extra == "ingest"
Requires-Dist: opentelemetry-sdk==1.29.0; extra == "ingest"
Requires-Dist: azure-core>=1.35.0; extra == "ingest"
Requires-Dist: azure-storage-blob>=12.26.0; extra == "ingest"
Requires-Dist: pyarrow>=21.0.0; extra == "ingest"
Provides-Extra: all
Requires-Dist: langchain-openai==0.2.8; extra == "all"
Requires-Dist: overrides==7.7.0; extra == "all"
Requires-Dist: tqdm==4.67.1; extra == "all"
Requires-Dist: opentelemetry-api==1.29.0; extra == "all"
Requires-Dist: opentelemetry-exporter-otlp==1.29.0; extra == "all"
Requires-Dist: opentelemetry-exporter-prometheus==0.50b0; extra == "all"
Requires-Dist: opentelemetry-instrumentation==0.50b0; extra == "all"
Requires-Dist: opentelemetry-instrumentation-fastapi==0.50b0; extra == "all"
Requires-Dist: opentelemetry-instrumentation-milvus==0.36.0; extra == "all"
Requires-Dist: opentelemetry-processor-baggage==0.50b0; extra == "all"
Requires-Dist: opentelemetry-sdk==1.29.0; extra == "all"
Requires-Dist: azure-core>=1.35.0; extra == "all"
Requires-Dist: azure-storage-blob>=12.26.0; extra == "all"
Requires-Dist: pyarrow>=21.0.0; extra == "all"
Dynamic: license-file
